[
  {
    "id": "mpr_policy_rates",
    "name": "Monetary Policy Report: Policy Rate Stance",
    "theme": "Policy",
    "description": "Front-end rates and policy stance indicators used to discuss current policy settings.",
    "source": {
      "name": "Federal Reserve Monetary Policy Report",
      "url": "https://www.federalreserve.gov/monetarypolicy/mpr_default.htm"
    },
    "default_chart_type": "line",
    "default_date_start": "2000-01-01",
    "series": [
      { "provider": "fred", "id": "FEDFUNDS", "alias": "FEDFUNDS", "title": "Federal Funds Effective Rate" },
      { "provider": "fred", "id": "SOFR", "alias": "SOFR", "title": "Secured Overnight Financing Rate" },
      { "provider": "fred", "id": "DFF", "alias": "DFF", "title": "Effective Federal Funds Rate (Daily)" },
      { "provider": "fred", "id": "DGS3MO", "alias": "DGS3MO", "title": "3-Month Treasury Yield" },
      { "provider": "fred", "id": "TB3MS", "alias": "TB3MS", "title": "3-Month Treasury Bill" }
    ],
    "formulas": [
      "SOFR_FF_GAP = SOFR - FEDFUNDS",
      "TBILL_FF_GAP = TB3MS - FEDFUNDS"
    ],
    "default_plot_vars": ["FEDFUNDS", "SOFR", "TB3MS", "SOFR_FF_GAP"]
  },
  {
    "id": "yield_curve_recession",
    "name": "Yield Curve Recession Watch",
    "theme": "Policy",
    "description": "Classic term spread monitoring with inversion flags and recession overlay variables.",
    "source": {
      "name": "Federal Reserve Selected Interest Rates (H.15)",
      "url": "https://www.federalreserve.gov/releases/h15/"
    },
    "default_chart_type": "yield_dashboard",
    "default_date_start": "1985-01-01",
    "series": [
      { "provider": "fred", "id": "GS10", "alias": "GS10", "title": "10-Year Treasury Constant Maturity" },
      { "provider": "fred", "id": "TB3MS", "alias": "TB3MS", "title": "3-Month Treasury Bill" },
      { "provider": "fred", "id": "T10Y3M", "alias": "T10Y3M", "title": "10Y - 3M Treasury Spread" },
      { "provider": "fred", "id": "T10Y2Y", "alias": "T10Y2Y", "title": "10Y - 2Y Treasury Spread" },
      { "provider": "fred", "id": "USREC", "alias": "USREC", "title": "NBER Recession Indicator" }
    ],
    "formulas": [
      "YC_SPREAD = GS10 - TB3MS",
      "YC_INVERTED = YC_SPREAD < 0"
    ],
    "default_plot_vars": ["GS10", "TB3MS", "YC_SPREAD", "USREC"]
  },
  {
    "id": "inflation_headline_core",
    "name": "Inflation: Headline vs Core",
    "theme": "Prices",
    "description": "Track headline and core inflation benchmarks across CPI and PCE families.",
    "source": {
      "name": "Federal Reserve Monetary Policy Report",
      "url": "https://www.federalreserve.gov/monetarypolicy/mpr_default.htm"
    },
    "default_chart_type": "line",
    "default_date_start": "1990-01-01",
    "series": [
      { "provider": "fred", "id": "CPIAUCSL", "alias": "CPIAUCSL", "title": "CPI: All Items" },
      { "provider": "fred", "id": "CPILFESL", "alias": "CPILFESL", "title": "Core CPI" },
      { "provider": "fred", "id": "PCEPI", "alias": "PCEPI", "title": "PCE Price Index" },
      { "provider": "fred", "id": "PCEPILFE", "alias": "PCEPILFE", "title": "Core PCE Price Index" },
      { "provider": "fred", "id": "PPIACO", "alias": "PPIACO", "title": "PPI: All Commodities" }
    ],
    "formulas": [
      "CORE_CPI_MINUS_CPI = CPILFESL - CPIAUCSL",
      "CORE_PCE_MINUS_PCE = PCEPILFE - PCEPI"
    ],
    "default_plot_vars": ["CPIAUCSL", "CPILFESL", "PCEPI", "PCEPILFE"]
  },
  {
    "id": "inflation_expectations",
    "name": "Inflation Expectations and Compensation",
    "theme": "Prices",
    "description": "Market-based inflation compensation and consumer inflation sentiment.",
    "source": {
      "name": "Federal Reserve Monetary Policy Report",
      "url": "https://www.federalreserve.gov/monetarypolicy/mpr_default.htm"
    },
    "default_chart_type": "line",
    "default_date_start": "2003-01-01",
    "series": [
      { "provider": "fred", "id": "T5YIE", "alias": "T5YIE", "title": "5-Year Breakeven Inflation" },
      { "provider": "fred", "id": "T10YIE", "alias": "T10YIE", "title": "10-Year Breakeven Inflation" },
      { "provider": "fred", "id": "T5YIFR", "alias": "T5YIFR", "title": "5-Year, 5-Year Forward Inflation Expectation Rate" },
      { "provider": "fred", "id": "MICH", "alias": "MICH", "title": "University of Michigan: Inflation Expectations" },
      { "provider": "fred", "id": "UMCSENT", "alias": "UMCSENT", "title": "University of Michigan: Consumer Sentiment" }
    ],
    "formulas": [
      "BEI_10_5_GAP = T10YIE - T5YIE"
    ],
    "default_plot_vars": ["T5YIE", "T10YIE", "T5YIFR", "MICH"]
  },
  {
    "id": "labor_market_slack",
    "name": "Labor Market Slack Dashboard",
    "theme": "Labor",
    "description": "Core labor utilization metrics and wage pressure indicators.",
    "source": {
      "name": "Federal Reserve Monetary Policy Report",
      "url": "https://www.federalreserve.gov/monetarypolicy/mpr_default.htm"
    },
    "default_chart_type": "line",
    "default_date_start": "1990-01-01",
    "series": [
      { "provider": "fred", "id": "UNRATE", "alias": "UNRATE", "title": "Unemployment Rate" },
      { "provider": "fred", "id": "U6RATE", "alias": "U6RATE", "title": "U-6 Unemployment Rate" },
      { "provider": "fred", "id": "PAYEMS", "alias": "PAYEMS", "title": "Total Nonfarm Payrolls" },
      { "provider": "fred", "id": "CIVPART", "alias": "CIVPART", "title": "Labor Force Participation Rate" },
      { "provider": "fred", "id": "CES0500000003", "alias": "AHE", "title": "Average Hourly Earnings" }
    ],
    "formulas": [
      "UNDEREMP_GAP = U6RATE - UNRATE"
    ],
    "default_plot_vars": ["UNRATE", "U6RATE", "CIVPART", "AHE"]
  },
  {
    "id": "labor_flows_jolts",
    "name": "Labor Flows: JOLTS Focus",
    "theme": "Labor",
    "description": "Openings, hires, quits, and layoffs to assess labor demand and churn.",
    "source": {
      "name": "Federal Reserve Beige Book",
      "url": "https://www.federalreserve.gov/monetarypolicy/beigebook/default.htm"
    },
    "default_chart_type": "line",
    "default_date_start": "2001-01-01",
    "series": [
      { "provider": "fred", "id": "JTSJOL", "alias": "JTSJOL", "title": "Job Openings" },
      { "provider": "fred", "id": "JTSHIR", "alias": "JTSHIR", "title": "Hires" },
      { "provider": "fred", "id": "JTSQUR", "alias": "JTSQUR", "title": "Quits" },
      { "provider": "fred", "id": "JTSLDL", "alias": "JTSLDL", "title": "Layoffs and Discharges" },
      { "provider": "fred", "id": "UNRATE", "alias": "UNRATE", "title": "Unemployment Rate" }
    ],
    "formulas": [
      "QUITS_MINUS_LAYOFFS = JTSQUR - JTSLDL"
    ],
    "default_plot_vars": ["JTSJOL", "JTSHIR", "JTSQUR", "JTSLDL"]
  },
  {
    "id": "growth_output_capacity",
    "name": "Output and Capacity",
    "theme": "Activity",
    "description": "Real activity and utilization indicators used to assess cyclical momentum.",
    "source": {
      "name": "Federal Reserve Industrial Production (G.17)",
      "url": "https://www.federalreserve.gov/releases/g17/current/"
    },
    "default_chart_type": "line",
    "default_date_start": "1980-01-01",
    "series": [
      { "provider": "fred", "id": "GDPC1", "alias": "GDPC1", "title": "Real GDP" },
      { "provider": "fred", "id": "GDP", "alias": "GDP", "title": "Nominal GDP" },
      { "provider": "fred", "id": "INDPRO", "alias": "INDPRO", "title": "Industrial Production Index" },
      { "provider": "fred", "id": "CUMFN", "alias": "CUMFN", "title": "Capacity Utilization" },
      { "provider": "fred", "id": "TCU", "alias": "TCU", "title": "Total Industry Capacity Utilization" }
    ],
    "formulas": [
      "REAL_NOMINAL_GAP = GDPC1 - GDP"
    ],
    "default_plot_vars": ["GDPC1", "INDPRO", "CUMFN", "TCU"]
  },
  {
    "id": "consumer_demand_income",
    "name": "Consumer Demand and Income",
    "theme": "Activity",
    "description": "Consumption, disposable income, savings, and retail channels.",
    "source": {
      "name": "Federal Reserve Monetary Policy Report",
      "url": "https://www.federalreserve.gov/monetarypolicy/mpr_default.htm"
    },
    "default_chart_type": "line",
    "default_date_start": "1992-01-01",
    "series": [
      { "provider": "fred", "id": "PCEC96", "alias": "PCEC96", "title": "Real Personal Consumption Expenditures" },
      { "provider": "fred", "id": "DSPIC96", "alias": "DSPIC96", "title": "Real Disposable Personal Income" },
      { "provider": "fred", "id": "PSAVERT", "alias": "PSAVERT", "title": "Personal Saving Rate" },
      { "provider": "fred", "id": "RSAFS", "alias": "RSAFS", "title": "Retail Sales" },
      { "provider": "fred", "id": "RRSFS", "alias": "RRSFS", "title": "Real Retail Sales" }
    ],
    "formulas": [
      "REAL_MINUS_NOMINAL_RETAIL = RRSFS - RSAFS"
    ],
    "default_plot_vars": ["PCEC96", "DSPIC96", "PSAVERT", "RRSFS"]
  },
  {
    "id": "housing_activity_finance",
    "name": "Housing Activity and Financing",
    "theme": "Housing",
    "description": "Residential construction, house prices, and mortgage-rate sensitivity.",
    "source": {
      "name": "Federal Reserve Monetary Policy Report",
      "url": "https://www.federalreserve.gov/monetarypolicy/mpr_default.htm"
    },
    "default_chart_type": "line",
    "default_date_start": "1990-01-01",
    "series": [
      { "provider": "fred", "id": "HOUST", "alias": "HOUST", "title": "Housing Starts" },
      { "provider": "fred", "id": "PERMIT", "alias": "PERMIT", "title": "Building Permits" },
      { "provider": "fred", "id": "CSUSHPINSA", "alias": "CSUSHPINSA", "title": "Case-Shiller Home Price Index" },
      { "provider": "fred", "id": "MORTGAGE30US", "alias": "MORTGAGE30US", "title": "30-Year Mortgage Rate" },
      { "provider": "fred", "id": "MSPUS", "alias": "MSPUS", "title": "Median Sales Price of Houses Sold" }
    ],
    "formulas": [
      "STARTS_PERMITS_GAP = HOUST - PERMIT"
    ],
    "default_plot_vars": ["HOUST", "PERMIT", "MORTGAGE30US", "CSUSHPINSA"]
  },
  {
    "id": "bank_credit_liquidity",
    "name": "Bank Credit and Liquidity",
    "theme": "Banking",
    "description": "Commercial bank credit growth and liquidity backdrop.",
    "source": {
      "name": "Federal Reserve Assets and Liabilities of Commercial Banks (H.8)",
      "url": "https://www.federalreserve.gov/releases/h8/current/"
    },
    "default_chart_type": "line",
    "default_date_start": "1990-01-01",
    "series": [
      { "provider": "fred", "id": "TOTBKCR", "alias": "TOTBKCR", "title": "Total Bank Credit" },
      { "provider": "fred", "id": "BUSLOANS", "alias": "BUSLOANS", "title": "Commercial and Industrial Loans" },
      { "provider": "fred", "id": "REALLN", "alias": "REALLN", "title": "Real Estate Loans" },
      { "provider": "fred", "id": "WRESBAL", "alias": "WRESBAL", "title": "Reserve Balances" },
      { "provider": "fred", "id": "WALCL", "alias": "WALCL", "title": "Federal Reserve Total Assets" }
    ],
    "formulas": [
      "C_I_TO_TOTAL = BUSLOANS / TOTBKCR"
    ],
    "default_plot_vars": ["TOTBKCR", "BUSLOANS", "REALLN", "WRESBAL"]
  },
  {
    "id": "fed_balance_sheet_reserves",
    "name": "Fed Balance Sheet Plumbing",
    "theme": "Banking",
    "description": "System liquidity channels: SOMA balance sheet, reserve balances, ON RRP, and TGA.",
    "source": {
      "name": "Federal Reserve Factors Affecting Reserve Balances (H.4.1)",
      "url": "https://www.federalreserve.gov/releases/h41/current/"
    },
    "default_chart_type": "line",
    "default_date_start": "2003-01-01",
    "series": [
      { "provider": "fred", "id": "WALCL", "alias": "WALCL", "title": "Federal Reserve Total Assets" },
      { "provider": "fred", "id": "WRESBAL", "alias": "WRESBAL", "title": "Reserve Balances" },
      { "provider": "fred", "id": "RRPONTSYD", "alias": "RRPONTSYD", "title": "Overnight Reverse Repo" },
      { "provider": "fred", "id": "RRPONTTLD", "alias": "RRPONTTLD", "title": "Overnight Reverse Repo - Total" },
      { "provider": "fred", "id": "WTREGEN", "alias": "WTREGEN", "title": "Treasury General Account" }
    ],
    "formulas": [
      "BALANCE_SHEET_NET_RRP = WALCL - RRPONTTLD"
    ],
    "default_plot_vars": ["WALCL", "WRESBAL", "RRPONTTLD", "WTREGEN"]
  },
  {
    "id": "money_stock_velocity",
    "name": "Money Stock and Velocity",
    "theme": "Money",
    "description": "Money aggregates and velocity for liquidity transmission context.",
    "source": {
      "name": "Federal Reserve Money Stock Measures (H.6)",
      "url": "https://www.federalreserve.gov/releases/h6/current/"
    },
    "default_chart_type": "line",
    "default_date_start": "1960-01-01",
    "series": [
      { "provider": "fred", "id": "M1SL", "alias": "M1SL", "title": "M1 Money Stock" },
      { "provider": "fred", "id": "M2SL", "alias": "M2SL", "title": "M2 Money Stock" },
      { "provider": "fred", "id": "M2V", "alias": "M2V", "title": "Velocity of M2" },
      { "provider": "fred", "id": "FEDFUNDS", "alias": "FEDFUNDS", "title": "Federal Funds Effective Rate" },
      { "provider": "fred", "id": "SOFR", "alias": "SOFR", "title": "SOFR" }
    ],
    "formulas": [
      "M2_TO_M1 = M2SL / M1SL"
    ],
    "default_plot_vars": ["M1SL", "M2SL", "M2V", "M2_TO_M1"]
  },
  {
    "id": "financial_conditions_risk",
    "name": "Financial Conditions and Market Risk",
    "theme": "Financial Stability",
    "description": "Stress and risk appetite indicators for financial-stability monitoring.",
    "source": {
      "name": "Federal Reserve Financial Stability Report",
      "url": "https://www.federalreserve.gov/publications/financial-stability-report.htm"
    },
    "default_chart_type": "line",
    "default_date_start": "1990-01-01",
    "series": [
      { "provider": "fred", "id": "NFCI", "alias": "NFCI", "title": "Chicago Fed National Financial Conditions Index" },
      { "provider": "fred", "id": "VIXCLS", "alias": "VIXCLS", "title": "CBOE VIX" },
      { "provider": "fred", "id": "TEDRATE", "alias": "TEDRATE", "title": "TED Spread" },
      { "provider": "fred", "id": "BAMLC0A4CBBB", "alias": "BBB_YLD", "title": "ICE BofA BBB Effective Yield" },
      { "provider": "fred", "id": "BAMLH0A0HYM2", "alias": "HY_OAS", "title": "ICE BofA High Yield OAS" }
    ],
    "formulas": [
      "RISK_MIX = VIXCLS + HY_OAS"
    ],
    "default_plot_vars": ["NFCI", "VIXCLS", "TEDRATE", "HY_OAS"]
  },
  {
    "id": "credit_spreads_quality",
    "name": "Credit Quality Ladder",
    "theme": "Financial Stability",
    "description": "Investment-grade versus speculative-grade spread structure.",
    "source": {
      "name": "Federal Reserve Financial Stability Report",
      "url": "https://www.federalreserve.gov/publications/financial-stability-report.htm"
    },
    "default_chart_type": "line",
    "default_date_start": "1997-01-01",
    "series": [
      { "provider": "fred", "id": "BAMLC0A1CAAAEY", "alias": "AAA_YLD", "title": "AAA Corporate Effective Yield" },
      { "provider": "fred", "id": "BAMLC0A4CBBB", "alias": "BBB_YLD", "title": "BBB Corporate Effective Yield" },
      { "provider": "fred", "id": "BAMLH0A3HYCEY", "alias": "CCC_YLD", "title": "CCC and Lower Effective Yield" },
      { "provider": "fred", "id": "BAA10Y", "alias": "BAA10Y", "title": "BAA - 10Y Treasury Spread" },
      { "provider": "fred", "id": "AAA10Y", "alias": "AAA10Y", "title": "AAA - 10Y Treasury Spread" }
    ],
    "formulas": [
      "JUNK_MINUS_AAA = CCC_YLD - AAA_YLD",
      "BBB_MINUS_AAA = BBB_YLD - AAA_YLD"
    ],
    "default_plot_vars": ["AAA_YLD", "BBB_YLD", "CCC_YLD", "JUNK_MINUS_AAA"]
  },
  {
    "id": "treasury_curve_full",
    "name": "Treasury Curve Shape",
    "theme": "Rates",
    "description": "Full-curve tenor comparisons used in policy and market briefings.",
    "source": {
      "name": "Federal Reserve Selected Interest Rates (H.15)",
      "url": "https://www.federalreserve.gov/releases/h15/"
    },
    "default_chart_type": "line",
    "default_date_start": "1990-01-01",
    "series": [
      { "provider": "fred", "id": "DGS1", "alias": "DGS1", "title": "1-Year Treasury Yield" },
      { "provider": "fred", "id": "DGS2", "alias": "DGS2", "title": "2-Year Treasury Yield" },
      { "provider": "fred", "id": "DGS5", "alias": "DGS5", "title": "5-Year Treasury Yield" },
      { "provider": "fred", "id": "DGS10", "alias": "DGS10", "title": "10-Year Treasury Yield" },
      { "provider": "fred", "id": "DGS30", "alias": "DGS30", "title": "30-Year Treasury Yield" }
    ],
    "formulas": [
      "CURVE_10_2 = DGS10 - DGS2",
      "CURVE_30_2 = DGS30 - DGS2"
    ],
    "default_plot_vars": ["DGS1", "DGS2", "DGS10", "DGS30", "CURVE_10_2"]
  },
  {
    "id": "dollar_fx_external",
    "name": "Dollar and Major FX Pairs",
    "theme": "External",
    "description": "Broad dollar index and major bilateral exchange rates.",
    "source": {
      "name": "Federal Reserve Selected Exchange Rates (H.10)",
      "url": "https://www.federalreserve.gov/releases/h10/current/"
    },
    "default_chart_type": "line",
    "default_date_start": "1995-01-01",
    "series": [
      { "provider": "fred", "id": "DTWEXBGS", "alias": "DTWEXBGS", "title": "Trade Weighted U.S. Dollar Index" },
      { "provider": "fred", "id": "DEXUSEU", "alias": "DEXUSEU", "title": "USD / Euro" },
      { "provider": "fred", "id": "DEXJPUS", "alias": "DEXJPUS", "title": "JPY / USD" },
      { "provider": "fred", "id": "DEXCHUS", "alias": "DEXCHUS", "title": "CNY / USD" },
      { "provider": "fred", "id": "DEXUSUK", "alias": "DEXUSUK", "title": "USD / GBP" }
    ],
    "formulas": [
      "USD_EUR_GBP = DEXUSEU + DEXUSUK"
    ],
    "default_plot_vars": ["DTWEXBGS", "DEXUSEU", "DEXJPUS", "DEXCHUS"]
  },
  {
    "id": "trade_external_balance",
    "name": "Trade and External Balance",
    "theme": "External",
    "description": "Goods/services trade dynamics and net export contribution context.",
    "source": {
      "name": "Federal Reserve Monetary Policy Report",
      "url": "https://www.federalreserve.gov/monetarypolicy/mpr_default.htm"
    },
    "default_chart_type": "line",
    "default_date_start": "1990-01-01",
    "series": [
      { "provider": "fred", "id": "BOPGSTB", "alias": "BOPGSTB", "title": "Trade Balance: Goods and Services" },
      { "provider": "fred", "id": "EXPGSC1", "alias": "EXPGSC1", "title": "Real Exports of Goods and Services" },
      { "provider": "fred", "id": "IMPGSC1", "alias": "IMPGSC1", "title": "Real Imports of Goods and Services" },
      { "provider": "fred", "id": "NETEXP", "alias": "NETEXP", "title": "Real Net Exports" },
      { "provider": "fred", "id": "BOPBCA", "alias": "BOPBCA", "title": "Current Account Balance" }
    ],
    "formulas": [
      "EXPORT_IMPORT_GAP = EXPGSC1 - IMPGSC1"
    ],
    "default_plot_vars": ["BOPGSTB", "NETEXP", "EXPGSC1", "IMPGSC1"]
  },
  {
    "id": "industrial_orders_inventory",
    "name": "Industrial Orders and Inventory",
    "theme": "Activity",
    "description": "Manufacturing orders and inventory pressure signals.",
    "source": {
      "name": "Federal Reserve Industrial Production (G.17)",
      "url": "https://www.federalreserve.gov/releases/g17/current/"
    },
    "default_chart_type": "line",
    "default_date_start": "1992-01-01",
    "series": [
      { "provider": "fred", "id": "INDPRO", "alias": "INDPRO", "title": "Industrial Production" },
      { "provider": "fred", "id": "IPMAN", "alias": "IPMAN", "title": "Manufacturing Production" },
      { "provider": "fred", "id": "AMTMNO", "alias": "AMTMNO", "title": "Manufacturers' New Orders" },
      { "provider": "fred", "id": "AMTMVS", "alias": "AMTMVS", "title": "Manufacturers' Total Inventories" },
      { "provider": "fred", "id": "ISRATIO", "alias": "ISRATIO", "title": "Business Inventories to Sales Ratio" }
    ],
    "formulas": [
      "ORDERS_INVENTORY_GAP = AMTMNO - AMTMVS"
    ],
    "default_plot_vars": ["INDPRO", "IPMAN", "AMTMNO", "AMTMVS", "ISRATIO"]
  },
  {
    "id": "consumer_credit_g19",
    "name": "Consumer Credit (G.19) Monitor",
    "theme": "Households",
    "description": "Total, revolving, and nonrevolving consumer credit with debt-service context.",
    "source": {
      "name": "Federal Reserve Consumer Credit (G.19)",
      "url": "https://www.federalreserve.gov/releases/g19/current/"
    },
    "default_chart_type": "line",
    "default_date_start": "1980-01-01",
    "series": [
      { "provider": "fred", "id": "TOTALSL", "alias": "TOTALSL", "title": "Total Consumer Credit" },
      { "provider": "fred", "id": "REVOLSL", "alias": "REVOLSL", "title": "Revolving Consumer Credit" },
      { "provider": "fred", "id": "NONREVSL", "alias": "NONREVSL", "title": "Nonrevolving Consumer Credit" },
      { "provider": "fred", "id": "TDSP", "alias": "TDSP", "title": "Household Debt Service Payments" },
      { "provider": "fred", "id": "DRCCLACBS", "alias": "DRCCLACBS", "title": "Credit Card Delinquency Rate" }
    ],
    "formulas": [
      "REVOLVING_SHARE = REVOLSL / TOTALSL",
      "NONREVOLVING_SHARE = NONREVSL / TOTALSL"
    ],
    "default_plot_vars": ["TOTALSL", "REVOLSL", "NONREVSL", "TDSP"]
  },
  {
    "id": "recession_monitor_composite",
    "name": "Composite Recession Monitor",
    "theme": "Cross-Market",
    "description": "Composite early-warning stack across curve, labor, activity, and financial conditions.",
    "source": {
      "name": "Federal Reserve Monetary Policy Report",
      "url": "https://www.federalreserve.gov/monetarypolicy/mpr_default.htm"
    },
    "default_chart_type": "line",
    "default_date_start": "1985-01-01",
    "series": [
      { "provider": "fred", "id": "USREC", "alias": "USREC", "title": "NBER Recession Indicator" },
      { "provider": "fred", "id": "T10Y3M", "alias": "T10Y3M", "title": "10Y - 3M Spread" },
      { "provider": "fred", "id": "UNRATE", "alias": "UNRATE", "title": "Unemployment Rate" },
      { "provider": "fred", "id": "PAYEMS", "alias": "PAYEMS", "title": "Payrolls" },
      { "provider": "fred", "id": "NFCI", "alias": "NFCI", "title": "National Financial Conditions Index" }
    ],
    "formulas": [
      "CURVE_INVERTED = T10Y3M < 0"
    ],
    "default_plot_vars": ["T10Y3M", "UNRATE", "NFCI", "USREC"]
  },
  {
    "id": "beige_book_crosscheck",
    "name": "Beige Book Hard-Data Cross-Check",
    "theme": "Cross-Market",
    "description": "Hard-data cross-check for anecdotal district conditions.",
    "source": {
      "name": "Federal Reserve Beige Book",
      "url": "https://www.federalreserve.gov/monetarypolicy/beigebook/default.htm"
    },
    "default_chart_type": "line",
    "default_date_start": "1990-01-01",
    "series": [
      { "provider": "fred", "id": "UNRATE", "alias": "UNRATE", "title": "Unemployment Rate" },
      { "provider": "fred", "id": "INDPRO", "alias": "INDPRO", "title": "Industrial Production" },
      { "provider": "fred", "id": "RSAFS", "alias": "RSAFS", "title": "Retail Sales" },
      { "provider": "fred", "id": "HOUST", "alias": "HOUST", "title": "Housing Starts" },
      { "provider": "fred", "id": "PPIACO", "alias": "PPIACO", "title": "Producer Prices" }
    ],
    "formulas": [
      "ACTIVITY_MINUS_UNEMP = INDPRO - UNRATE"
    ],
    "default_plot_vars": ["UNRATE", "INDPRO", "RSAFS", "HOUST", "PPIACO"]
  },
  {
    "id": "regional_housing_split",
    "name": "Regional Housing Starts Split",
    "theme": "Housing",
    "description": "Regional decomposition of housing-start dynamics.",
    "source": {
      "name": "Federal Reserve Monetary Policy Report",
      "url": "https://www.federalreserve.gov/monetarypolicy/mpr_default.htm"
    },
    "default_chart_type": "line",
    "default_date_start": "1990-01-01",
    "series": [
      { "provider": "fred", "id": "HOUST", "alias": "HOUST", "title": "Housing Starts: Total" },
      { "provider": "fred", "id": "HOUSTNE", "alias": "HOUSTNE", "title": "Housing Starts: Northeast" },
      { "provider": "fred", "id": "HOUSTMW", "alias": "HOUSTMW", "title": "Housing Starts: Midwest" },
      { "provider": "fred", "id": "HOUSTS", "alias": "HOUSTS", "title": "Housing Starts: South" },
      { "provider": "fred", "id": "HOUSTW", "alias": "HOUSTW", "title": "Housing Starts: West" }
    ],
    "formulas": [
      "REGION_SUM = HOUSTNE + HOUSTMW + HOUSTS + HOUSTW"
    ],
    "default_plot_vars": ["HOUST", "HOUSTNE", "HOUSTMW", "HOUSTS", "HOUSTW"]
  },
  {
    "id": "energy_and_inflation_pass",
    "name": "Energy Prices and Inflation Pass-Through",
    "theme": "Prices",
    "description": "Crude oil and producer/consumer prices for pass-through discussion.",
    "source": {
      "name": "Federal Reserve Monetary Policy Report",
      "url": "https://www.federalreserve.gov/monetarypolicy/mpr_default.htm"
    },
    "default_chart_type": "line",
    "default_date_start": "1990-01-01",
    "series": [
      { "provider": "fred", "id": "DCOILWTICO", "alias": "DCOILWTICO", "title": "WTI Crude Oil Price" },
      { "provider": "fred", "id": "PPIACO", "alias": "PPIACO", "title": "Producer Price Index" },
      { "provider": "fred", "id": "CPIAUCSL", "alias": "CPIAUCSL", "title": "Consumer Price Index" },
      { "provider": "fred", "id": "CPILFESL", "alias": "CPILFESL", "title": "Core CPI" },
      { "provider": "fred", "id": "PCEPI", "alias": "PCEPI", "title": "PCE Price Index" }
    ],
    "formulas": [
      "HEADLINE_CORE_CPI_GAP = CPIAUCSL - CPILFESL"
    ],
    "default_plot_vars": ["DCOILWTICO", "PPIACO", "CPIAUCSL", "CPILFESL"]
  },
  {
    "id": "slack_rule_of_thumb",
    "name": "Slack and Policy Rule-of-Thumb",
    "theme": "Policy",
    "description": "Simple dashboard combining policy rate, unemployment slack proxy, and inflation measures.",
    "source": {
      "name": "Federal Reserve Monetary Policy Report",
      "url": "https://www.federalreserve.gov/monetarypolicy/mpr_default.htm"
    },
    "default_chart_type": "line",
    "default_date_start": "1990-01-01",
    "series": [
      { "provider": "fred", "id": "FEDFUNDS", "alias": "FEDFUNDS", "title": "Federal Funds Rate" },
      { "provider": "fred", "id": "UNRATE", "alias": "UNRATE", "title": "Unemployment Rate" },
      { "provider": "fred", "id": "NROU", "alias": "NROU", "title": "Natural Rate of Unemployment" },
      { "provider": "fred", "id": "PCEPI", "alias": "PCEPI", "title": "PCE Price Index" },
      { "provider": "fred", "id": "PCEPILFE", "alias": "PCEPILFE", "title": "Core PCE" }
    ],
    "formulas": [
      "UNEMP_GAP = UNRATE - NROU",
      "CORE_HEADLINE_PCE_GAP = PCEPILFE - PCEPI"
    ],
    "default_plot_vars": ["FEDFUNDS", "UNRATE", "NROU", "UNEMP_GAP"]
  },
  {
    "id": "bls_fred_crosswalk",
    "name": "BLS + FRED Crosswalk",
    "theme": "Data QA",
    "description": "Cross-source reference panel using BLS-native series alongside FRED mirrors.",
    "source": {
      "name": "Federal Reserve FRED and BLS Public API",
      "url": "https://fred.stlouisfed.org/docs/api/fred/"
    },
    "default_chart_type": "line",
    "default_date_start": "1990-01-01",
    "series": [
      { "provider": "bls", "id": "LNS14000000", "alias": "BLS_UNRATE", "title": "BLS Unemployment Rate" },
      { "provider": "bls", "id": "CES0000000001", "alias": "BLS_PAYEMS", "title": "BLS Total Nonfarm Payrolls" },
      { "provider": "bls", "id": "CUUR0000SA0", "alias": "BLS_CPI", "title": "BLS CPI-U" },
      { "provider": "fred", "id": "UNRATE", "alias": "UNRATE", "title": "FRED Unemployment Rate" },
      { "provider": "fred", "id": "CPIAUCSL", "alias": "CPIAUCSL", "title": "FRED CPI-U" }
    ],
    "formulas": [
      "UNRATE_SOURCE_GAP = BLS_UNRATE - UNRATE",
      "CPI_SOURCE_GAP = BLS_CPI - CPIAUCSL"
    ],
    "default_plot_vars": ["BLS_UNRATE", "UNRATE", "BLS_CPI", "CPIAUCSL"]
  }
]
